APACHE-LICENSE-2.0.txt
CHANGES.txt
COPYRIGHT.txt
LICENSE.txt
PKG-INFO
README.txt
TODO.txt
buildout.cfg
ez_setup.py
setup.cfg
setup.py
cp/.DS_Store
cp/__init__.py
cp.buildout_postgres.egg-info/PKG-INFO
cp.buildout_postgres.egg-info/SOURCES.txt
cp.buildout_postgres.egg-info/dependency_links.txt
cp.buildout_postgres.egg-info/entry_points.txt
cp.buildout_postgres.egg-info/namespace_packages.txt
cp.buildout_postgres.egg-info/requires.txt
cp.buildout_postgres.egg-info/top_level.txt
cp.buildout_postgres.egg-info/zip-safe
cp/buildout_postgres/__init__.py
cp/buildout_postgres/apachectl.in
cp/buildout_postgres/defaults.cfg
cp/buildout_postgres/httpd.conf.in
cp/buildout_postgres/httpd.py
cp/buildout_postgres/orig_tests.txt
cp/buildout_postgres/pg_hba.conf.in
cp/buildout_postgres/pg_ident.conf.in
cp/buildout_postgres/postgres.py
cp/buildout_postgres/postgresql.conf.in
cp/buildout_postgres/root.py
cp/buildout_postgres/root.txt
cp/buildout_postgres/tests.py
tests/.DS_Store
tests/README.txt
tests/buildout.cfg