Metadata-Version: 1.0
Name: cp.buildout-postgres
Version: 0.1-r2723
Summary: zc.buildout recipes for setting up a Postgres Environment.
Home-page: http://pypi.python.org/pypi/cp.buildout_postgres
Author: Craig Sawyer
Author-email: csawyer@yumaed.org
License: ZPL 2.1
Keywords: buildout zc.buildout recipe postgres database server instance
Platform: UNKNOWN
Classifier: Development Status :: 3 - Alpha
Classifier: Environment :: Console
Classifier: Environment :: Plugins
Classifier: Framework :: Buildout
Classifier: Intended Audience :: Developers
Classifier: Intended Audience :: System Administrators
Classifier: License :: OSI Approved :: Zope Public License
Classifier: Operating System :: OS Independent
Classifier: Programming Language :: Python
Classifier: Topic :: Software Development :: Build Tools
Classifier: Topic :: System :: Software Distribution
